custom/build.py
rtctree_build_idl-1.0.4.dist-info/METADATA
rtctree_build_idl-1.0.4.dist-info/WHEEL
rtctree_build_idl-1.0.4.dist-info/entry_points.txt
rtctree_build_idl-1.0.4.dist-info/top_level.txt
rtctree_build_idl-1.0.4.dist-info/RECORD
