Metadata-Version: 2.4
Name: rtctree-build-idl
Version: 1.0.4
Summary: Custom build/installation commands for rtctree.
Author: Noriaki Ando
Author-email: n-ando@aist.go.jp
License: LGPL-3.0-or-later
Project-URL: Source, https://github.com/OpenRTM/rtctree-build-idl
Requires-Python: >=3.9
